bonltk/__init__.py
bonltk/_nbdev.py
bonltk/text_quality.py
bonltk/text_sim.py
bonltk-0.0.4.dist-info/LICENSE
bonltk-0.0.4.dist-info/METADATA
bonltk-0.0.4.dist-info/WHEEL
bonltk-0.0.4.dist-info/entry_points.txt
bonltk-0.0.4.dist-info/top_level.txt
bonltk-0.0.4.dist-info/RECORD
