Metadata-Version: 2.1
Name: bonltk
Version: 0.0.4
Summary: BoNLTK aims to provide out of the box support for various NLP tasks that an application developer might need for Boyig (TIbetan) language.
Home-page: https://github.com/Esukhia/bonltk
Author: Tenzin
Author-email: 10zin@esukhia.org
License: Apache Software License 2.0
Keywords: nlp lstm pytorch fastai language-model
Platform: UNKNOWN
Classifier: Development Status :: 3 - Alpha
Classifier: Intended Audience :: Developers
Classifier: License :: OSI Approved :: Apache Software License
Classifier: Natural Language :: English
Classifier: Programming Language :: Python :: 3.6
Classifier: Programming Language :: Python :: 3.7
Classifier: Programming Language :: Python :: 3.8
Requires-Python: >=3.6
Requires-Dist: botok
